aiocryptopay/__init__.py
aiocryptopay/api.py
aiocryptopay/base.py
aiocryptopay/const.py
aiocryptopay/exceptions/__init__.py
aiocryptopay/exceptions/factory.py
aiocryptopay/models/__init__.py
aiocryptopay/models/app_stats.py
aiocryptopay/models/balance.py
aiocryptopay/models/check.py
aiocryptopay/models/currencies.py
aiocryptopay/models/invoice.py
aiocryptopay/models/profile.py
aiocryptopay/models/rates.py
aiocryptopay/models/transfer.py
aiocryptopay/models/update.py
aiocryptopay/utils/__init__.py
aiocryptopay/utils/exchange.py
aiocryptopay-0.4.6.dist-info/LICENSE
aiocryptopay-0.4.6.dist-info/METADATA
aiocryptopay-0.4.6.dist-info/WHEEL
aiocryptopay-0.4.6.dist-info/RECORD
