Metadata-Version: 2.1
Name: aiocryptopay
Version: 0.4.6
Summary: @cryptobot api asynchronous python wrapper
Home-page: https://github.com/layerqa/aiocryptopay
License: MIT
Keywords: aiocryptopay,cryptobot,cryptopay,cryptopay api,cryptobot api
Author: layerqa
Requires-Python: >=3.8,<4.0
Classifier: License :: OSI Approved :: MIT License
Classifier: Programming Language :: Python :: 3
Classifier: Programming Language :: Python :: 3.8
Classifier: Programming Language :: Python :: 3.9
Classifier: Programming Language :: Python :: 3.10
Classifier: Programming Language :: Python :: 3.11
Classifier: Programming Language :: Python :: 3.12
Requires-Dist: aiohttp (>=3.8.3,<4.0.0)
Requires-Dist: certifi (>=2023.5.7,<2024.0.0)
Requires-Dist: pydantic (>=2.4.1,<3.0.0)
Requires-Dist: strenum (>=0.4.10,<0.5.0)
Project-URL: Documentation, https://help.crypt.bot/crypto-pay-api
Project-URL: Repository, https://github.com/layerqa/aiocryptopay
